{
    "file_name": "n-2021-06-11-131052-mn-3a-001_1-6IdiGMQA9jX2OhXC2OTtdYmX_cam1_00398.jpg",
    "predictions": [
        {
            "category_id": 2,
            "bbox": [
                294.1540832519531,
                1715.037841796875,
                588.3081665039062,
                370.1453857421875
            ],
            "score": 0.92167729139328
        },
        {
            "category_id": 2,
            "bbox": [
                1937.344970703125,
                1333.343505859375,
                231.8687744140625,
                239.7154541015625
            ],
            "score": 0.9127073287963867
        },
        {
            "category_id": 2,
            "bbox": [
                1021.7935791015625,
                1345.30712890625,
                269.09588623046875,
                189.3687744140625
            ],
            "score": 0.902974545955658
        },
        {
            "category_id": 2,
            "bbox": [
                1408.83251953125,
                1191.6802978515625,
                120.6387939453125,
                85.51171875
            ],
            "score": 0.9000855088233948
        },
        {
            "category_id": 2,
            "bbox": [
                1520.828369140625,
                1136.8551025390625,
                97.2603759765625,
                65.629638671875
            ],
            "score": 0.8955989480018616
        },
        {
            "category_id": 2,
            "bbox": [
                1670.17138671875,
                1125.16064453125,
                88.650390625,
                72.4302978515625
            ],
            "score": 0.8787768483161926
        }
    ]
}