{
    "file_name": "n-2021-03-08-133933-mn-3a-001_1-6092MTPSuvDp6mbwyGzxz9Qj_cam1_00357.jpg",
    "predictions": [
        {
            "category_id": 1,
            "bbox": [
                2236.3486328125,
                1720.38720703125,
                402.128662109375,
                316.298583984375
            ],
            "score": 0.9270148873329163
        },
        {
            "category_id": 2,
            "bbox": [
                1513.02001953125,
                780.6478271484375,
                64.5968017578125,
                54.5753173828125
            ],
            "score": 0.9187302589416504
        },
        {
            "category_id": 2,
            "bbox": [
                2238.83642578125,
                928.5469970703125,
                389.966064453125,
                142.92120361328125
            ],
            "score": 0.803821861743927
        },
        {
            "category_id": 0,
            "bbox": [
                786.0126953125,
                875.1786499023438,
                56.22821044921875,
                62.10888671875
            ],
            "score": 0.7671259045600891
        },
        {
            "category_id": 0,
            "bbox": [
                392.30181884765625,
                1138.36669921875,
                73.03939819335938,
                172.2020263671875
            ],
            "score": 0.564791738986969
        },
        {
            "category_id": 0,
            "bbox": [
                795.9236450195312,
                874.161865234375,
                57.283447265625,
                59.11309814453125
            ],
            "score": 0.4982915222644806
        },
        {
            "category_id": 2,
            "bbox": [
                1429.674072265625,
                747.765625,
                53.5252685546875,
                46.27655029296875
            ],
            "score": 0.3512600064277649
        },
        {
            "category_id": 0,
            "bbox": [
                775.7169799804688,
                877.603759765625,
                58.1016845703125,
                59.445556640625
            ],
            "score": 0.28271788358688354
        }
    ]
}