{
    "file_name": "n-2021-03-08-104608-mn-3a-001_0-vNmFUNbucStoMnkBkFGn1C94_cam1_00370.jpg",
    "predictions": [
        {
            "category_id": 2,
            "bbox": [
                621.0883178710938,
                664.5380249023438,
                138.0819091796875,
                65.8787841796875
            ],
            "score": 0.9003301858901978
        },
        {
            "category_id": 2,
            "bbox": [
                1388.3974609375,
                793.2513427734375,
                290.1270751953125,
                134.63360595703125
            ],
            "score": 0.8833590149879456
        },
        {
            "category_id": 2,
            "bbox": [
                1438.4840087890625,
                632.9283447265625,
                182.96875,
                86.2149658203125
            ],
            "score": 0.8616210222244263
        },
        {
            "category_id": 2,
            "bbox": [
                154.63916015625,
                682.54248046875,
                120.76787567138672,
                75.27362060546875
            ],
            "score": 0.8502450585365295
        },
        {
            "category_id": 2,
            "bbox": [
                40.829017639160156,
                645.5830078125,
                79.80538940429688,
                71.11163330078125
            ],
            "score": 0.6245561242103577
        },
        {
            "category_id": 2,
            "bbox": [
                69.61414337158203,
                653.1774291992188,
                112.75704193115234,
                68.549560546875
            ],
            "score": 0.5532011985778809
        },
        {
            "category_id": 2,
            "bbox": [
                112.96256256103516,
                670.4229736328125,
                112.80879211425781,
                68.83831787109375
            ],
            "score": 0.34942638874053955
        }
    ]
}