{
    "file_name": "n-2021-03-08-133933-mn-3a-001_1-6092MTPSuvDp6mbwyGzxz9Qj_cam1_00300.jpg",
    "predictions": [
        {
            "category_id": 1,
            "bbox": [
                2236.38671875,
                1720.08447265625,
                401.9669189453125,
                316.8623046875
            ],
            "score": 0.927051305770874
        },
        {
            "category_id": 2,
            "bbox": [
                1513.2674560546875,
                780.898681640625,
                64.168212890625,
                53.55328369140625
            ],
            "score": 0.924117386341095
        },
        {
            "category_id": 2,
            "bbox": [
                1337.29052734375,
                896.8182983398438,
                136.8890380859375,
                133.8275146484375
            ],
            "score": 0.9092276692390442
        },
        {
            "category_id": 2,
            "bbox": [
                2229.205810546875,
                929.9599609375,
                362.78564453125,
                133.4876708984375
            ],
            "score": 0.7963608503341675
        },
        {
            "category_id": 0,
            "bbox": [
                786.2835693359375,
                876.9847412109375,
                53.99371337890625,
                57.7882080078125
            ],
            "score": 0.7496859431266785
        },
        {
            "category_id": 0,
            "bbox": [
                795.9461669921875,
                875.8133544921875,
                52.3675537109375,
                56.57281494140625
            ],
            "score": 0.7307329177856445
        },
        {
            "category_id": 2,
            "bbox": [
                30.927265167236328,
                958.6788330078125,
                61.37152862548828,
                107.17584228515625
            ],
            "score": 0.7009931802749634
        },
        {
            "category_id": 0,
            "bbox": [
                775.226806640625,
                879.1668701171875,
                57.58074951171875,
                56.62371826171875
            ],
            "score": 0.36603984236717224
        },
        {
            "category_id": 0,
            "bbox": [
                1893.4326171875,
                936.3179931640625,
                55.7254638671875,
                127.46722412109375
            ],
            "score": 0.31449633836746216
        }
    ]
}