{
    "file_name": "nneo_pcd_customdata-s6nwj6hi-defaultproject-0DF2qxDAtKbdBLxXN88aiQDO_00284.pcd.jpg",
    "predictions": [
        {
            "category_id": 2,
            "bbox": [
                1127.3118896484375,
                1678.554931640625,
                663.931640625,
                738.89013671875
            ],
            "score": 0.9403362274169922
        },
        {
            "category_id": 2,
            "bbox": [
                2029.527587890625,
                1014.935302734375,
                389.5196533203125,
                202.01849365234375
            ],
            "score": 0.9279038310050964
        },
        {
            "category_id": 2,
            "bbox": [
                1501.4730224609375,
                861.0393676757812,
                177.98388671875,
                131.1051025390625
            ],
            "score": 0.9046716690063477
        },
        {
            "category_id": 2,
            "bbox": [
                1074.8336181640625,
                1047.973388671875,
                208.10040283203125,
                215.30511474609375
            ],
            "score": 0.8988674879074097
        },
        {
            "category_id": 2,
            "bbox": [
                2324.05810546875,
                1235.34814453125,
                247.69677734375,
                237.6407470703125
            ],
            "score": 0.8804848194122314
        },
        {
            "category_id": 2,
            "bbox": [
                1092.5457763671875,
                912.5506591796875,
                163.04248046875,
                179.9974365234375
            ],
            "score": 0.8699277639389038
        },
        {
            "category_id": 2,
            "bbox": [
                1086.528564453125,
                847.234619140625,
                136.86798095703125,
                128.53387451171875
            ],
            "score": 0.7949073314666748
        },
        {
            "category_id": 1,
            "bbox": [
                667.703369140625,
                1392.698486328125,
                265.00823974609375,
                151.8466796875
            ],
            "score": 0.7944561243057251
        },
        {
            "category_id": 2,
            "bbox": [
                1437.74658203125,
                745.020751953125,
                85.6119384765625,
                67.6339111328125
            ],
            "score": 0.7677428126335144
        },
        {
            "category_id": 0,
            "bbox": [
                483.35894775390625,
                1143.2967529296875,
                88.98727416992188,
                241.26519775390625
            ],
            "score": 0.7659820914268494
        },
        {
            "category_id": 1,
            "bbox": [
                599.10888671875,
                1446.335693359375,
                300.36553955078125,
                170.7545166015625
            ],
            "score": 0.7641056180000305
        },
        {
            "category_id": 0,
            "bbox": [
                1422.2705078125,
                1072.0728759765625,
                114.37841796875,
                213.30889892578125
            ],
            "score": 0.7526098489761353
        },
        {
            "category_id": 1,
            "bbox": [
                649.7093505859375,
                1411.555908203125,
                281.80938720703125,
                150.057861328125
            ],
            "score": 0.7440498471260071
        },
        {
            "category_id": 1,
            "bbox": [
                627.2265625,
                1430.271240234375,
                267.5566711425781,
                157.4661865234375
            ],
            "score": 0.7021564245223999
        },
        {
            "category_id": 0,
            "bbox": [
                2251.98974609375,
                926.6431884765625,
                60.347412109375,
                164.7586669921875
            ],
            "score": 0.536466121673584
        },
        {
            "category_id": 2,
            "bbox": [
                1501.72265625,
                759.8392333984375,
                123.0181884765625,
                65.0059814453125
            ],
            "score": 0.41769012808799744
        },
        {
            "category_id": 0,
            "bbox": [
                2266.6708984375,
                925.638427734375,
                72.712890625,
                166.11834716796875
            ],
            "score": 0.38516801595687866
        }
    ]
}