{
    "file_name": "n-2021-05-10-135125-mn-3a-001_0-MYvvg0l3k8LXv0pUwNLjHD6Q_cam1_00707.jpg",
    "predictions": [
        {
            "category_id": 2,
            "bbox": [
                371.75262451171875,
                868.1730346679688,
                159.44790649414062,
                102.882568359375
            ],
            "score": 0.9246192574501038
        },
        {
            "category_id": 2,
            "bbox": [
                1512.214599609375,
                871.1668701171875,
                149.3509521484375,
                101.09332275390625
            ],
            "score": 0.9092009663581848
        },
        {
            "category_id": 2,
            "bbox": [
                442.5316467285156,
                1158.2135009765625,
                670.9876098632812,
                279.60760498046875
            ],
            "score": 0.8997326493263245
        },
        {
            "category_id": 2,
            "bbox": [
                531.550048828125,
                877.133056640625,
                137.13824462890625,
                99.76470947265625
            ],
            "score": 0.8923448920249939
        },
        {
            "category_id": 2,
            "bbox": [
                183.00099182128906,
                874.1788940429688,
                172.45993041992188,
                104.9708251953125
            ],
            "score": 0.8864538073539734
        },
        {
            "category_id": 2,
            "bbox": [
                1356.447021484375,
                802.72412109375,
                91.80419921875,
                68.77508544921875
            ],
            "score": 0.873924970626831
        },
        {
            "category_id": 2,
            "bbox": [
                816.410400390625,
                818.1907958984375,
                83.35906982421875,
                71.281005859375
            ],
            "score": 0.8602770566940308
        },
        {
            "category_id": 2,
            "bbox": [
                1063.071533203125,
                823.3392333984375,
                83.33099365234375,
                89.02740478515625
            ],
            "score": 0.8580899834632874
        },
        {
            "category_id": 2,
            "bbox": [
                693.1185302734375,
                813.1517944335938,
                96.54705810546875,
                66.4344482421875
            ],
            "score": 0.841952383518219
        },
        {
            "category_id": 2,
            "bbox": [
                562.8109741210938,
                814.6973876953125,
                103.92599487304688,
                75.02313232421875
            ],
            "score": 0.8382349014282227
        },
        {
            "category_id": 0,
            "bbox": [
                949.1903686523438,
                983.8404541015625,
                58.6844482421875,
                145.30645751953125
            ],
            "score": 0.7968661189079285
        },
        {
            "category_id": 2,
            "bbox": [
                76.77505493164062,
                868.7922973632812,
                136.4405517578125,
                110.2125244140625
            ],
            "score": 0.7961296439170837
        },
        {
            "category_id": 0,
            "bbox": [
                835.3763427734375,
                1065.4517822265625,
                60.17779541015625,
                156.9482421875
            ],
            "score": 0.7009146213531494
        },
        {
            "category_id": 0,
            "bbox": [
                1500.436767578125,
                975.744384765625,
                59.6241455078125,
                123.64129638671875
            ],
            "score": 0.6839868426322937
        },
        {
            "category_id": 0,
            "bbox": [
                907.3768310546875,
                987.2134399414062,
                57.23956298828125,
                145.0028076171875
            ],
            "score": 0.6649806499481201
        },
        {
            "category_id": 2,
            "bbox": [
                66.1554183959961,
                788.3773193359375,
                132.3108367919922,
                97.7431640625
            ],
            "score": 0.6374637484550476
        },
        {
            "category_id": 0,
            "bbox": [
                920.253173828125,
                984.0971069335938,
                64.51300048828125,
                144.0372314453125
            ],
            "score": 0.4542868435382843
        },
        {
            "category_id": 2,
            "bbox": [
                82.47209167480469,
                808.7598266601562,
                114.5631103515625,
                73.1788330078125
            ],
            "score": 0.3783155083656311
        }
    ]
}