{
    "file_name": "n-2021-03-08-133933-mn-3a-001_1-6092MTPSuvDp6mbwyGzxz9Qj_cam1_00818.jpg",
    "predictions": [
        {
            "category_id": 1,
            "bbox": [
                2233.2197265625,
                1713.8837890625,
                415.9310302734375,
                315.2281494140625
            ],
            "score": 0.9274645447731018
        },
        {
            "category_id": 2,
            "bbox": [
                668.3271484375,
                1780.25927734375,
                835.7265625,
                524.4031982421875
            ],
            "score": 0.9264035224914551
        },
        {
            "category_id": 2,
            "bbox": [
                1515.510986328125,
                780.5037841796875,
                67.826904296875,
                51.0867919921875
            ],
            "score": 0.8125104904174805
        },
        {
            "category_id": 0,
            "bbox": [
                1459.961181640625,
                877.1602783203125,
                59.5765380859375,
                90.24493408203125
            ],
            "score": 0.7081906795501709
        },
        {
            "category_id": 0,
            "bbox": [
                800.8787841796875,
                874.50341796875,
                73.37701416015625,
                66.2987060546875
            ],
            "score": 0.4877319931983948
        },
        {
            "category_id": 0,
            "bbox": [
                811.0328369140625,
                870.8748779296875,
                65.04205322265625,
                72.2421875
            ],
            "score": 0.4794822335243225
        }
    ]
}