{
    "file_name": "n-2021-05-12-144651-mn-3a-001_0_1-2-BzE2oWp2SAPhm6orp6Rg6Knd_cam1_00759.jpg",
    "predictions": [
        {
            "category_id": 2,
            "bbox": [
                849.6912841796875,
                1495.09912109375,
                422.32928466796875,
                571.55078125
            ],
            "score": 0.9497271180152893
        },
        {
            "category_id": 2,
            "bbox": [
                1003.9510498046875,
                867.0955200195312,
                64.70135498046875,
                53.9970703125
            ],
            "score": 0.8369004726409912
        },
        {
            "category_id": 2,
            "bbox": [
                756.49169921875,
                877.7230224609375,
                59.0853271484375,
                51.06378173828125
            ],
            "score": 0.8355495929718018
        },
        {
            "category_id": 2,
            "bbox": [
                416.4159240722656,
                879.0952758789062,
                88.0450439453125,
                64.3857421875
            ],
            "score": 0.8308245539665222
        },
        {
            "category_id": 2,
            "bbox": [
                325.86724853515625,
                919.0300903320312,
                82.673828125,
                73.069091796875
            ],
            "score": 0.7987996339797974
        },
        {
            "category_id": 2,
            "bbox": [
                325.079345703125,
                888.4786376953125,
                71.494873046875,
                60.2911376953125
            ],
            "score": 0.755475640296936
        },
        {
            "category_id": 2,
            "bbox": [
                409.349365234375,
                921.179443359375,
                91.51409912109375,
                70.70361328125
            ],
            "score": 0.5330212116241455
        }
    ]
}