{
    "file_name": "n-2021-03-19-084444-mn-3a-001_0-fRy10oxd0mRedgBtNtxkKNMF_cam1_00088.jpg",
    "predictions": [
        {
            "category_id": 2,
            "bbox": [
                540.3931274414062,
                1332.3258056640625,
                423.1535949707031,
                644.5624389648438
            ],
            "score": 0.9208683371543884
        },
        {
            "category_id": 2,
            "bbox": [
                542.7867431640625,
                1929.7916259765625,
                522.8182373046875,
                230.4013671875
            ],
            "score": 0.7752305269241333
        },
        {
            "category_id": 0,
            "bbox": [
                774.6909790039062,
                1279.013427734375,
                69.130615234375,
                158.1336669921875
            ],
            "score": 0.5142345428466797
        }
    ]
}