{
    "file_name": "n-2021-05-12-144651-mn-3a-001_0_1-2-BzE2oWp2SAPhm6orp6Rg6Knd_cam1_00859.jpg",
    "predictions": [
        {
            "category_id": 2,
            "bbox": [
                850.0391845703125,
                1494.841552734375,
                421.98858642578125,
                572.0906982421875
            ],
            "score": 0.9511440396308899
        },
        {
            "category_id": 2,
            "bbox": [
                585.923828125,
                1025.0794677734375,
                347.9417724609375,
                130.78631591796875
            ],
            "score": 0.8460166454315186
        },
        {
            "category_id": 2,
            "bbox": [
                416.098388671875,
                878.6458129882812,
                91.93679809570312,
                64.039794921875
            ],
            "score": 0.8305251598358154
        },
        {
            "category_id": 2,
            "bbox": [
                757.2259521484375,
                877.8053588867188,
                59.68621826171875,
                52.4527587890625
            ],
            "score": 0.8144996166229248
        },
        {
            "category_id": 2,
            "bbox": [
                1004.227294921875,
                866.754150390625,
                64.14996337890625,
                54.1578369140625
            ],
            "score": 0.8031274676322937
        },
        {
            "category_id": 2,
            "bbox": [
                325.7900390625,
                919.7913818359375,
                82.10769653320312,
                70.88861083984375
            ],
            "score": 0.8005121946334839
        },
        {
            "category_id": 2,
            "bbox": [
                324.676513671875,
                887.90087890625,
                70.49957275390625,
                59.17120361328125
            ],
            "score": 0.7705000042915344
        },
        {
            "category_id": 2,
            "bbox": [
                401.3130187988281,
                919.18408203125,
                89.94781494140625,
                75.31585693359375
            ],
            "score": 0.4627354145050049
        }
    ]
}