{
    "file_name": "n-2021-05-10-094421-mn-3a-001_0-RfartYdBMvVCdRFZLvlnpNwP_cam1_00086.jpg",
    "predictions": [
        {
            "category_id": 2,
            "bbox": [
                1038.0478515625,
                1765.52392578125,
                647.9102172851562,
                561.4605712890625
            ],
            "score": 0.9264316558837891
        },
        {
            "category_id": 0,
            "bbox": [
                410.7034606933594,
                1290.700439453125,
                119.346435546875,
                281.4447021484375
            ],
            "score": 0.7905443906784058
        },
        {
            "category_id": 0,
            "bbox": [
                287.9523010253906,
                1294.572509765625,
                107.24607849121094,
                267.7847900390625
            ],
            "score": 0.294002503156662
        }
    ]
}