{
    "file_name": "n-2021-03-04-131813-mn-3a-001_0-19wKSHkBQAVzX53pMCshpauD_cam1_01266.jpg",
    "predictions": [
        {
            "category_id": 2,
            "bbox": [
                2324.06005859375,
                786.007080078125,
                207.542724609375,
                90.39788818359375
            ],
            "score": 0.8918729424476624
        },
        {
            "category_id": 2,
            "bbox": [
                1124.36767578125,
                783.34326171875,
                184.6759033203125,
                75.78961181640625
            ],
            "score": 0.8880917429924011
        },
        {
            "category_id": 2,
            "bbox": [
                147.8601531982422,
                928.6221313476562,
                295.7203063964844,
                116.8021240234375
            ],
            "score": 0.8629855513572693
        },
        {
            "category_id": 2,
            "bbox": [
                1874.970458984375,
                779.0101318359375,
                82.4737548828125,
                68.43975830078125
            ],
            "score": 0.8584742546081543
        },
        {
            "category_id": 2,
            "bbox": [
                72.91819763183594,
                1024.225830078125,
                144.86935424804688,
                154.0015869140625
            ],
            "score": 0.8352365493774414
        }
    ]
}