{
    "file_name": "n-2021-05-10-135125-mn-3a-001_0-MYvvg0l3k8LXv0pUwNLjHD6Q_cam1_00134.jpg",
    "predictions": [
        {
            "category_id": 2,
            "bbox": [
                372.5772705078125,
                868.1334838867188,
                157.20095825195312,
                103.090576171875
            ],
            "score": 0.9287042021751404
        },
        {
            "category_id": 2,
            "bbox": [
                1511.16064453125,
                872.12109375,
                145.7393798828125,
                100.51165771484375
            ],
            "score": 0.9123006463050842
        },
        {
            "category_id": 2,
            "bbox": [
                185.23834228515625,
                872.3258056640625,
                169.84185791015625,
                105.72845458984375
            ],
            "score": 0.8871663808822632
        },
        {
            "category_id": 2,
            "bbox": [
                532.4749145507812,
                876.5648193359375,
                140.645751953125,
                97.64605712890625
            ],
            "score": 0.8861081600189209
        },
        {
            "category_id": 2,
            "bbox": [
                815.2035522460938,
                818.1012573242188,
                85.9156494140625,
                70.33447265625
            ],
            "score": 0.8684097528457642
        },
        {
            "category_id": 2,
            "bbox": [
                1356.87939453125,
                802.525634765625,
                91.2767333984375,
                68.70782470703125
            ],
            "score": 0.8672837615013123
        },
        {
            "category_id": 2,
            "bbox": [
                692.1622314453125,
                813.92431640625,
                98.96044921875,
                68.47271728515625
            ],
            "score": 0.8572278618812561
        },
        {
            "category_id": 2,
            "bbox": [
                1066.1719970703125,
                822.0906982421875,
                84.87420654296875,
                86.35430908203125
            ],
            "score": 0.8568558096885681
        },
        {
            "category_id": 2,
            "bbox": [
                75.00942993164062,
                868.406005859375,
                134.56240844726562,
                108.94366455078125
            ],
            "score": 0.8508188128471375
        },
        {
            "category_id": 2,
            "bbox": [
                558.7518310546875,
                813.3182373046875,
                105.08755493164062,
                76.2364501953125
            ],
            "score": 0.844047486782074
        },
        {
            "category_id": 0,
            "bbox": [
                956.0035400390625,
                976.00927734375,
                52.562255859375,
                138.35784912109375
            ],
            "score": 0.8395112752914429
        },
        {
            "category_id": 0,
            "bbox": [
                903.678466796875,
                988.9949951171875,
                60.85443115234375,
                142.56988525390625
            ],
            "score": 0.791851282119751
        },
        {
            "category_id": 0,
            "bbox": [
                1237.78076171875,
                969.73828125,
                74.0135498046875,
                126.08782958984375
            ],
            "score": 0.7734036445617676
        },
        {
            "category_id": 3,
            "bbox": [
                2181.856689453125,
                1070.96533203125,
                532.2867431640625,
                307.1346435546875
            ],
            "score": 0.7566775679588318
        },
        {
            "category_id": 2,
            "bbox": [
                67.17291259765625,
                792.5036010742188,
                133.7850341796875,
                92.70654296875
            ],
            "score": 0.7357643842697144
        },
        {
            "category_id": 1,
            "bbox": [
                2181.795654296875,
                1066.375244140625,
                530.5166015625,
                312.20928955078125
            ],
            "score": 0.2655271291732788
        }
    ]
}