{
    "file_name": "n-2021-03-09-085350-mn-3a-001_0-MTCjh5Hg98Pl08Ln5AbsYnWq_cam1_00121.jpg",
    "predictions": [
        {
            "category_id": 2,
            "bbox": [
                798.7099609375,
                1484.4735107421875,
                317.16009521484375,
                203.6728515625
            ],
            "score": 0.930761992931366
        },
        {
            "category_id": 2,
            "bbox": [
                1662.265869140625,
                1446.636962890625,
                160.9296875,
                166.7984619140625
            ],
            "score": 0.879530668258667
        },
        {
            "category_id": 2,
            "bbox": [
                1024.329833984375,
                1367.872802734375,
                144.4696044921875,
                115.99755859375
            ],
            "score": 0.869111180305481
        },
        {
            "category_id": 2,
            "bbox": [
                1123.5413818359375,
                1302.888916015625,
                153.081787109375,
                126.922607421875
            ],
            "score": 0.8564156889915466
        },
        {
            "category_id": 2,
            "bbox": [
                1212.412841796875,
                1247.8037109375,
                130.1910400390625,
                133.295166015625
            ],
            "score": 0.7989675402641296
        },
        {
            "category_id": 2,
            "bbox": [
                1493.99267578125,
                1220.57958984375,
                76.3790283203125,
                69.1773681640625
            ],
            "score": 0.726055920124054
        },
        {
            "category_id": 2,
            "bbox": [
                1671.6502685546875,
                1376.1978759765625,
                128.505859375,
                108.4365234375
            ],
            "score": 0.7035072445869446
        },
        {
            "category_id": 2,
            "bbox": [
                1770.007568359375,
                1790.9896240234375,
                625.7965087890625,
                499.638671875
            ],
            "score": 0.6039842963218689
        },
        {
            "category_id": 2,
            "bbox": [
                1264.270751953125,
                1227.001708984375,
                87.2890625,
                97.2137451171875
            ],
            "score": 0.5522949695587158
        },
        {
            "category_id": 2,
            "bbox": [
                1630.5728759765625,
                1273.880859375,
                99.398681640625,
                96.8231201171875
            ],
            "score": 0.4988291263580322
        },
        {
            "category_id": 2,
            "bbox": [
                1626.9866943359375,
                1218.188720703125,
                97.4833984375,
                83.2940673828125
            ],
            "score": 0.4486343562602997
        },
        {
            "category_id": 2,
            "bbox": [
                1231.662841796875,
                1241.165283203125,
                119.9613037109375,
                127.50537109375
            ],
            "score": 0.41477036476135254
        },
        {
            "category_id": 2,
            "bbox": [
                1278.10400390625,
                1222.7962646484375,
                89.2144775390625,
                82.9990234375
            ],
            "score": 0.2532360553741455
        }
    ]
}