{
    "file_name": "n-2021-03-08-144651-mn-3a-001_0-mNSzBuqLmlavp2KsOtEYO3l3_cam1_00229.jpg",
    "predictions": [
        {
            "category_id": 2,
            "bbox": [
                1210.3812255859375,
                867.865478515625,
                70.93505859375,
                53.3489990234375
            ],
            "score": 0.8155742883682251
        },
        {
            "category_id": 0,
            "bbox": [
                1030.6336669921875,
                1171.249755859375,
                65.902587890625,
                160.282470703125
            ],
            "score": 0.718673050403595
        },
        {
            "category_id": 2,
            "bbox": [
                1219.19775390625,
                864.6817626953125,
                66.3201904296875,
                52.1212158203125
            ],
            "score": 0.6614920496940613
        },
        {
            "category_id": 0,
            "bbox": [
                2016.7353515625,
                1382.3671875,
                92.64501953125,
                290.5692138671875
            ],
            "score": 0.6610169410705566
        }
    ]
}