{
    "file_name": "n-2021-03-08-104608-mn-3a-001_0-vNmFUNbucStoMnkBkFGn1C94_cam1_00724.jpg",
    "predictions": [
        {
            "category_id": 2,
            "bbox": [
                1440.000244140625,
                633.827880859375,
                191.715087890625,
                86.83502197265625
            ],
            "score": 0.9054588079452515
        },
        {
            "category_id": 2,
            "bbox": [
                625.705810546875,
                662.4913330078125,
                138.00909423828125,
                66.54083251953125
            ],
            "score": 0.8681437969207764
        },
        {
            "category_id": 2,
            "bbox": [
                151.3733673095703,
                679.606689453125,
                116.97013092041016,
                71.96575927734375
            ],
            "score": 0.791729211807251
        },
        {
            "category_id": 2,
            "bbox": [
                39.028316497802734,
                643.2092895507812,
                78.05663299560547,
                64.198974609375
            ],
            "score": 0.7068900465965271
        },
        {
            "category_id": 2,
            "bbox": [
                86.94305419921875,
                656.0826416015625,
                108.65595245361328,
                65.59368896484375
            ],
            "score": 0.576537549495697
        },
        {
            "category_id": 2,
            "bbox": [
                94.24642944335938,
                664.966796875,
                102.22528076171875,
                64.52642822265625
            ],
            "score": 0.4866611361503601
        },
        {
            "category_id": 2,
            "bbox": [
                2202.77001953125,
                675.167236328125,
                141.787353515625,
                95.13592529296875
            ],
            "score": 0.4640326499938965
        },
        {
            "category_id": 2,
            "bbox": [
                60.40541076660156,
                651.6929931640625,
                90.7540283203125,
                67.68878173828125
            ],
            "score": 0.4560941755771637
        }
    ]
}