{
    "file_name": "nneo_pcd_customdata-s6nwj6hi-defaultproject-0BT0g87H71kDEZXkeGvgkP0o_00368.pcd.jpg",
    "predictions": [
        {
            "category_id": 2,
            "bbox": [
                1942.2608642578125,
                1649.7666015625,
                485.343017578125,
                577.4892578125
            ],
            "score": 0.9401684403419495
        },
        {
            "category_id": 2,
            "bbox": [
                1025.201416015625,
                1243.471435546875,
                407.3680419921875,
                304.6365966796875
            ],
            "score": 0.9348399043083191
        },
        {
            "category_id": 2,
            "bbox": [
                831.104736328125,
                884.441650390625,
                220.21539306640625,
                86.42120361328125
            ],
            "score": 0.9260720610618591
        },
        {
            "category_id": 2,
            "bbox": [
                234.10745239257812,
                897.3656005859375,
                192.12815856933594,
                85.84478759765625
            ],
            "score": 0.8908251523971558
        },
        {
            "category_id": 2,
            "bbox": [
                402.4008483886719,
                1597.75927734375,
                804.8016967773438,
                900.4815673828125
            ],
            "score": 0.8745553493499756
        },
        {
            "category_id": 2,
            "bbox": [
                720.8512573242188,
                1186.8135986328125,
                460.611572265625,
                256.643310546875
            ],
            "score": 0.8741508722305298
        },
        {
            "category_id": 2,
            "bbox": [
                403.80120849609375,
                1739.299072265625,
                806.58544921875,
                617.4017333984375
            ],
            "score": 0.8652859330177307
        },
        {
            "category_id": 0,
            "bbox": [
                273.3722839355469,
                1146.19140625,
                63.54609680175781,
                164.690673828125
            ],
            "score": 0.5976684093475342
        },
        {
            "category_id": 0,
            "bbox": [
                81.46276092529297,
                1168.19580078125,
                80.67715454101562,
                151.0286865234375
            ],
            "score": 0.5765268206596375
        },
        {
            "category_id": 2,
            "bbox": [
                307.3981018066406,
                1455.761474609375,
                614.7962036132812,
                502.0830078125
            ],
            "score": 0.39588090777397156
        },
        {
            "category_id": 0,
            "bbox": [
                89.15560913085938,
                1200.248291015625,
                68.54055786132812,
                209.7864990234375
            ],
            "score": 0.31098857522010803
        },
        {
            "category_id": 2,
            "bbox": [
                249.435791015625,
                1500.73779296875,
                498.87158203125,
                532.4119873046875
            ],
            "score": 0.2817001938819885
        }
    ]
}