{
    "file_name": "nneo_pcd_customdata-s6nwj6hi-defaultproject-0BT0g87H71kDEZXkeGvgkP0o_00602.pcd.jpg",
    "predictions": [
        {
            "category_id": 2,
            "bbox": [
                1939.8828125,
                1649.359619140625,
                488.8828125,
                577.65478515625
            ],
            "score": 0.942612886428833
        },
        {
            "category_id": 2,
            "bbox": [
                829.8397216796875,
                884.39208984375,
                220.2625732421875,
                87.62640380859375
            ],
            "score": 0.9401847124099731
        },
        {
            "category_id": 2,
            "bbox": [
                1285.7686767578125,
                1571.27490234375,
                548.22119140625,
                550.3223876953125
            ],
            "score": 0.9357936978340149
        },
        {
            "category_id": 2,
            "bbox": [
                717.0836181640625,
                1198.11865234375,
                468.9417419433594,
                278.7384033203125
            ],
            "score": 0.929571270942688
        },
        {
            "category_id": 2,
            "bbox": [
                1518.316162109375,
                1147.156494140625,
                310.3875732421875,
                278.97943115234375
            ],
            "score": 0.9236972332000732
        },
        {
            "category_id": 2,
            "bbox": [
                251.94151306152344,
                1495.6307373046875,
                503.8830261230469,
                557.413330078125
            ],
            "score": 0.9210072755813599
        },
        {
            "category_id": 2,
            "bbox": [
                232.27345275878906,
                899.93994140625,
                192.34579467773438,
                82.43896484375
            ],
            "score": 0.87760990858078
        },
        {
            "category_id": 0,
            "bbox": [
                142.083251953125,
                1167.572265625,
                74.23129272460938,
                175.7874755859375
            ],
            "score": 0.8509706258773804
        },
        {
            "category_id": 2,
            "bbox": [
                1594.4620361328125,
                808.4068603515625,
                87.571044921875,
                65.278564453125
            ],
            "score": 0.8318992257118225
        }
    ]
}