{
    "file_name": "nneo_pcd_customdata-s6nwj6hi-defaultproject-0DF2qxDAtKbdBLxXN88aiQDO_00175.pcd.jpg",
    "predictions": [
        {
            "category_id": 2,
            "bbox": [
                2031.24658203125,
                1017.97216796875,
                386.3792724609375,
                201.06146240234375
            ],
            "score": 0.9342342615127563
        },
        {
            "category_id": 2,
            "bbox": [
                1133.9234619140625,
                1677.032470703125,
                666.803466796875,
                741.93505859375
            ],
            "score": 0.9227805733680725
        },
        {
            "category_id": 2,
            "bbox": [
                1075.668212890625,
                1051.183837890625,
                204.94189453125,
                218.7386474609375
            ],
            "score": 0.9049729704856873
        },
        {
            "category_id": 2,
            "bbox": [
                2327.66015625,
                1240.325927734375,
                240.679443359375,
                236.8182373046875
            ],
            "score": 0.8938884139060974
        },
        {
            "category_id": 2,
            "bbox": [
                1093.6357421875,
                916.7033081054688,
                159.71807861328125,
                177.797607421875
            ],
            "score": 0.8789916634559631
        },
        {
            "category_id": 2,
            "bbox": [
                1496.290283203125,
                769.9579467773438,
                121.7818603515625,
                75.7740478515625
            ],
            "score": 0.8785095810890198
        },
        {
            "category_id": 2,
            "bbox": [
                1088.7076416015625,
                848.4564208984375,
                139.48876953125,
                139.8121337890625
            ],
            "score": 0.8530530333518982
        },
        {
            "category_id": 1,
            "bbox": [
                599.21630859375,
                1427.137451171875,
                310.7088928222656,
                206.2841796875
            ],
            "score": 0.8198481202125549
        },
        {
            "category_id": 1,
            "bbox": [
                646.6698608398438,
                1396.5672607421875,
                304.8404235839844,
                150.58837890625
            ],
            "score": 0.8009294867515564
        },
        {
            "category_id": 2,
            "bbox": [
                1436.367919921875,
                744.2718505859375,
                90.2156982421875,
                69.5233154296875
            ],
            "score": 0.7988497614860535
        },
        {
            "category_id": 2,
            "bbox": [
                1123.0450439453125,
                707.685302734375,
                60.119140625,
                51.43414306640625
            ],
            "score": 0.7964492440223694
        },
        {
            "category_id": 0,
            "bbox": [
                364.8016357421875,
                1346.18212890625,
                121.80978393554688,
                368.679931640625
            ],
            "score": 0.7871691584587097
        },
        {
            "category_id": 0,
            "bbox": [
                2399.74609375,
                841.7613525390625,
                56.122802734375,
                91.92120361328125
            ],
            "score": 0.3296965956687927
        },
        {
            "category_id": 2,
            "bbox": [
                1478.766845703125,
                758.265869140625,
                113.2596435546875,
                77.61102294921875
            ],
            "score": 0.2665926218032837
        }
    ]
}